qtlizlib/__init__.py
qtlizlib/cli.py
qtlizlib/scripts.py
qtlizlib/domain/__init__.py
qtlizlib/domain/config.py
qtlizlib/domain/menuActionTool.py
qtlizlib/domain/preference.py
qtlizlib/domain/resource.py
qtlizlib/domain/theme.py
qtlizlib/handler/__init__.py
qtlizlib/handler/config.py
qtlizlib/handler/menuAction.py
qtlizlib/handler/menuActionInst.py
qtlizlib/handler/menuActionToolbar.py
qtlizlib/handler/operation.py
qtlizlib/handler/resource.py
qtlizlib/helper/__init__.py
qtlizlib/helper/operation.py
qtlizlib/model/__init__.py
qtlizlib/model/menuActionTool.py
qtlizlib/util/__init__.py
qtlizlib/util/menuActionTool.py
qtlizlib/util/preference.py
qtlizlib/util/qtlizLogger.py
qtlizlib/widget/__init__.py
qtlizlib/widget/data.py
qtlizlib/widget/status.py
qtliz-0.1.16.dist-info/METADATA
qtliz-0.1.16.dist-info/WHEEL
qtliz-0.1.16.dist-info/entry_points.txt
qtliz-0.1.16.dist-info/top_level.txt
qtliz-0.1.16.dist-info/RECORD
