Metadata-Version: 2.4
Name: qtliz
Version: 0.1.16
Summary: Add your description here
Requires-Python: >=3.12
Requires-Dist: pylizlib>=0.1.46
Requires-Dist: pyside6>=6.9.0
Requires-Dist: rich>=14.0.0
Requires-Dist: typer>=0.15.2
